{
  "snapshot": "kernelDidInitialize",
  "timestamp": "2026-06-06T10:30:24.904Z",
  "id": "EntityClassRegistry:Default",
  "nodeId": "EntityClassRegistry",
  "instanceId": "Default",
  "props": {
    "parentId": "Root:Default"
  },
  "parentId": "Root:Default",
  "constants": {},
  "metaDataSchemas": {},
  "metaData": {
    "description": "The Entity Class Manager page, where the user manages the registry of entity classes (the types of things modeled, such as plugin or theme): list them and create, rename/edit, or delete a class."
  },
  "coreDataSchemas": {},
  "coreData": {},
  "runtimeDataSchemas": {},
  "runtimeData": {},
  "optionSchemas": {},
  "options": {},
  "coreFunctionSchemas": {},
  "coreFunctions": {},
  "buildArtifactSchemas": {},
  "buildArtifacts": {},
  "signalGroups": {},
  "optimisticSignals": {},
  "executionContext": "mainApp",
  "_nodeResources": {
    "nodeId": "EntityClassRegistry",
    "configDirSubPath": "nodes/EntityClassRegistry",
    "executionContext": "mainApp",
    "rootModuleId": "Root",
    "config": {
      "parentId": null,
      "defaultPaths": {
        "modules": "/",
        "components": "/components",
        "kernelFragments": "/kernel"
      },
      "styles": {
        "inherit": true
      },
      "autoDiscover": {}
    },
    "constants": {},
    "metaDataSchemas": {},
    "metaData": {
      "description": "The Entity Class Manager page, where the user manages the registry of entity classes (the types of things modeled, such as plugin or theme): list them and create, rename/edit, or delete a class."
    },
    "coreDataSchemas": {},
    "coreData": {},
    "runtimeDataSchemas": {},
    "runtimeData": {},
    "optionSchemas": {},
    "options": {},
    "signalGroups": {},
    "signals": {},
    "modules": {
      "Root": {
        "isRoot": true,
        "description": "The page that lists all entity classes and lets the user view, create, edit, and delete a class, shown beneath the \"Entity Class Manager\" heading.",
        "component": "[fn:Root]",
        "subPath": "nodes/EntityClassRegistry/Root",
        "inheritanceLevel": "echo"
      }
    },
    "components": {
      "PageHeaderAlpha": {
        "isGlobal": true,
        "component": "[fn:PageHeaderAlpha]",
        "subPath": "globals/components/PageHeaderAlpha",
        "inheritanceLevel": "echo"
      }
    },
    "moduleProps": {},
    "instances": {
      "Default": {
        "metaData": {
          "description": "The Entity Class Manager page, where the user manages the registry of entity classes (the types of things modeled, such as plugin or theme): list them and create, rename/edit, or delete a class."
        },
        "coreData": {},
        "options": {},
        "moduleProps": {},
        "hooks": {},
        "nodeEvents": {},
        "nodeEventHandlers": {},
        "appEventHandlers": {},
        "coreFunctions": {}
      }
    },
    "kernelFragments": {},
    "hooks": {},
    "nodeEvents": {},
    "nodeEventHandlers": {},
    "appEventHandlers": {},
    "coreFunctionSchemas": {},
    "coreFunctions": {},
    "buildScripts": {},
    "buildArtifacts": {},
    "buildArtifactSchemas": {},
    "styles": {
      "inherit": true,
      "content": null,
      "concatenatedFrom": []
    },
    "kernelMethods": {},
    "inheritanceChain": {
      "alpha": {
        "nodeId": null,
        "exists": false
      },
      "bravo": {
        "nodeId": null,
        "exists": false
      },
      "charlie": {
        "nodeId": null,
        "exists": false
      },
      "delta": {
        "nodeId": null,
        "exists": false
      },
      "echo": {
        "nodeId": "EntityClassRegistry",
        "exists": true
      }
    },
    "KernelClass": "[fn:CompiledNodeKernel]"
  },
  "runtimeDataDidChange": "[fn:runtimeDataDidChange]",
  "_e$": "[fn:anonymous]"
}